[
  {
    "__template_key": "bilibili",
    "enable": true,
    "use_proxy": false,
    "cookies": "",
    "video_codec_list": [
      "AVC",
      "AV1",
      "HEV"
    ],
    "video_quality": "_720P"
  },
  {
    "__template_key": "douyin",
    "enable": true,
    "use_proxy": false,
    "cookies": ""
  },
  {
    "__template_key": "kuaishou",
    "enable": true,
    "use_proxy": false,
    "cookies": ""
  },
  {
    "__template_key": "weibo",
    "enable": true,
    "use_proxy": false,
    "cookies": ""
  },
  {
    "__template_key": "xhs",
    "enable": true,
    "use_proxy": false,
    "cookies": ""
  },
  {
    "__template_key": "xiaoheihe",
    "enable": true,
    "use_proxy": false,
    "cookies": "",
    "show_body_text": true,
    "video_send_mode": "first"
  }
]
